yamlarg/__init__.py
yamlarg-0.0.8.dist-info/LICENSE
yamlarg-0.0.8.dist-info/METADATA
yamlarg-0.0.8.dist-info/WHEEL
yamlarg-0.0.8.dist-info/entry_points.txt
yamlarg-0.0.8.dist-info/top_level.txt
yamlarg-0.0.8.dist-info/RECORD
