Metadata-Version: 2.1
Name: yamlarg
Version: 0.0.8
Summary: Easy YAML arguments for python scripts.
Home-page: https://github.com/alphabet5/yamlarg
Author: John Burt
Author-email: 
License: UNKNOWN
Platform: UNKNOWN
Classifier: Programming Language :: Python :: 3
Classifier: License :: OSI Approved :: Apache Software License
Classifier: Operating System :: OS Independent
Requires-Python: >=3.6
License-File: LICENSE
